lg_linter/__init__.py
lg_linter/config/.clang-format
lg_linter/config/.pylintrc
lg_linter/config/.style.yapf
lg_linter/config/CPPLINT.cfg
lg_linter/scripts/__init__.py
lg_linter/scripts/deinit_lg_linter
lg_linter/scripts/init_lg_linter
lg_linter/scripts/lint_repo
lg_linter/src/__init__.py
lg_linter/src/file_linters.py
lg_linter/src/lg_linter.py
lg_linter-0.1.7.data/scripts/deinit_lg_linter
lg_linter-0.1.7.data/scripts/init_lg_linter
lg_linter-0.1.7.data/scripts/lint_repo
lg_linter-0.1.7.dist-info/LICENCE
lg_linter-0.1.7.dist-info/METADATA
lg_linter-0.1.7.dist-info/WHEEL
lg_linter-0.1.7.dist-info/top_level.txt
lg_linter-0.1.7.dist-info/RECORD
