Metadata-Version: 2.1
Name: lg-linter
Version: 0.1.7
Summary: A pre commit linter for cpp, python and sh.
Home-page: https://github.com/lgulich/lg-linter
Author: Lionel Gulich
Author-email: lgulich@ethz.ch
License: GPL-3.0
Download-URL: https://github.com/lgulich/lg-linter/archive/v0.1.7.tar.gz
Platform: UNKNOWN
Classifier: Programming Language :: Python :: 3 :: Only
Classifier: License :: OSI Approved :: GNU General Public License v3 (GPLv3)
Classifier: Operating System :: POSIX :: Linux
Classifier: Natural Language :: English
Requires-Python: >=3.6
Requires-Dist: gitpython
Requires-Dist: pylint
Requires-Dist: yapf
Requires-Dist: cpplint
